MANIFEST.in
README.md
setup.py
.eggs/numpy-1.15.1-py2.7-macosx-10.6-x86_64.egg/numpy/core/include/numpy/__multiarray_api.h
.eggs/numpy-1.15.1-py2.7-macosx-10.6-x86_64.egg/numpy/core/include/numpy/__ufunc_api.h
.eggs/numpy-1.15.1-py2.7-macosx-10.6-x86_64.egg/numpy/core/include/numpy/_neighborhood_iterator_imp.h
.eggs/numpy-1.15.1-py2.7-macosx-10.6-x86_64.egg/numpy/core/include/numpy/_numpyconfig.h
.eggs/numpy-1.15.1-py2.7-macosx-10.6-x86_64.egg/numpy/core/include/numpy/arrayobject.h
.eggs/numpy-1.15.1-py2.7-macosx-10.6-x86_64.egg/numpy/core/include/numpy/arrayscalars.h
.eggs/numpy-1.15.1-py2.7-macosx-10.6-x86_64.egg/numpy/core/include/numpy/halffloat.h
.eggs/numpy-1.15.1-py2.7-macosx-10.6-x86_64.egg/numpy/core/include/numpy/ndarrayobject.h
.eggs/numpy-1.15.1-py2.7-macosx-10.6-x86_64.egg/numpy/core/include/numpy/ndarraytypes.h
.eggs/numpy-1.15.1-py2.7-macosx-10.6-x86_64.egg/numpy/core/include/numpy/noprefix.h
.eggs/numpy-1.15.1-py2.7-macosx-10.6-x86_64.egg/numpy/core/include/numpy/npy_1_7_deprecated_api.h
.eggs/numpy-1.15.1-py2.7-macosx-10.6-x86_64.egg/numpy/core/include/numpy/npy_3kcompat.h
.eggs/numpy-1.15.1-py2.7-macosx-10.6-x86_64.egg/numpy/core/include/numpy/npy_common.h
.eggs/numpy-1.15.1-py2.7-macosx-10.6-x86_64.egg/numpy/core/include/numpy/npy_cpu.h
.eggs/numpy-1.15.1-py2.7-macosx-10.6-x86_64.egg/numpy/core/include/numpy/npy_endian.h
.eggs/numpy-1.15.1-py2.7-macosx-10.6-x86_64.egg/numpy/core/include/numpy/npy_interrupt.h
.eggs/numpy-1.15.1-py2.7-macosx-10.6-x86_64.egg/numpy/core/include/numpy/npy_math.h
.eggs/numpy-1.15.1-py2.7-macosx-10.6-x86_64.egg/numpy/core/include/numpy/npy_no_deprecated_api.h
.eggs/numpy-1.15.1-py2.7-macosx-10.6-x86_64.egg/numpy/core/include/numpy/npy_os.h
.eggs/numpy-1.15.1-py2.7-macosx-10.6-x86_64.egg/numpy/core/include/numpy/numpyconfig.h
.eggs/numpy-1.15.1-py2.7-macosx-10.6-x86_64.egg/numpy/core/include/numpy/old_defines.h
.eggs/numpy-1.15.1-py2.7-macosx-10.6-x86_64.egg/numpy/core/include/numpy/oldnumeric.h
jpeg2dct.egg-info/PKG-INFO
jpeg2dct.egg-info/SOURCES.txt
jpeg2dct.egg-info/dependency_links.txt
jpeg2dct.egg-info/not-zip-safe
jpeg2dct.egg-info/requires.txt
jpeg2dct.egg-info/top_level.txt
