Metadata-Version: 1.0
Name: jpeg2dct
Version: 0.2.2
Summary: Library providing a Python function and a TensorFlow Op to read JPEG image as a numpy 
Home-page: https://github.com/uber-research/jpeg2dct
Author: Uber Technologies, Inc.
Author-email: UNKNOWN
License: UNKNOWN
Platform: UNKNOWN
